rettxmutation/__init__.py
rettxmutation/config.py
rettxmutation/models/__init__.py
rettxmutation/models/context.py
rettxmutation/models/document.py
rettxmutation/models/gene_assembly.py
rettxmutation/models/gene_models.py
rettxmutation/models/gene_registry.py
rettxmutation/models/keyword_collection.py
rettxmutation/models/mutation_model.py
rettxmutation/models/search_models.py
rettxmutation/openai_agent/__init__.py
rettxmutation/openai_agent/base_agent.py
rettxmutation/openai_agent/embedding_client.py
rettxmutation/openai_agent/exceptions.py
rettxmutation/openai_agent/hardcoded_prompts.py
rettxmutation/openai_agent/hardcoded_yaml_configs.py
rettxmutation/openai_agent/mutation_extraction_agent.py
rettxmutation/openai_agent/summarization_agent.py
rettxmutation/openai_agent/utils.py
rettxmutation/openai_agent/validation_agent.py
rettxmutation/openai_agent/prompts/__init__.py
rettxmutation/openai_agent/prompts/extraction/__init__.py
rettxmutation/openai_agent/prompts/extraction/extract_mutations.skprompt.txt
rettxmutation/openai_agent/prompts/extraction/extract_mutations.yaml
rettxmutation/openai_agent/prompts/shared/__init__.py
rettxmutation/openai_agent/prompts/shared/latest_transcripts.json
rettxmutation/openai_agent/prompts/summarization/__init__.py
rettxmutation/openai_agent/prompts/summarization/correct_summary_mistakes.skprompt.txt
rettxmutation/openai_agent/prompts/summarization/correct_summary_mistakes.yaml
rettxmutation/openai_agent/prompts/summarization/summarize_report.skprompt.txt
rettxmutation/openai_agent/prompts/summarization/summarize_report.yaml
rettxmutation/openai_agent/prompts/validation/__init__.py
rettxmutation/openai_agent/prompts/validation/validate_document.skprompt.txt
rettxmutation/openai_agent/prompts/validation/validate_document.yaml
rettxmutation/openai_agent/prompts/validation/validate_mutations.skprompt.txt
rettxmutation/openai_agent/prompts/validation/validate_mutations.yaml
rettxmutation/repositories/__init__.py
rettxmutation-0.1.12.dist-info/licenses/LICENSE
rettxmutation-0.1.12.dist-info/METADATA
rettxmutation-0.1.12.dist-info/WHEEL
rettxmutation-0.1.12.dist-info/top_level.txt
rettxmutation-0.1.12.dist-info/RECORD
