Metadata-Version: 2.4
Name: rettxmutation
Version: 0.1.12
Summary: Extract Rett Syndrome mutations from genetic diagnosis report
Author-email: Pedro Rocha <procha@rettsyndrome.eu>
License: MIT License
Project-URL: Homepage, https://github.com/rett-europe/rettxmutation
Project-URL: Issues, https://github.com/rett-europe/rettxmutation/issues
Classifier: Programming Language :: Python :: 3
Classifier: License :: OSI Approved :: MIT License
Classifier: Operating System :: OS Independent
Requires-Python: >=3.8
License-File: LICENSE
Requires-Dist: python-dotenv
Requires-Dist: azure-ai-formrecognizer
Requires-Dist: azure-core
Requires-Dist: azure-ai-textanalytics
Requires-Dist: azure.ai.documentintelligence
Requires-Dist: ftfy
Requires-Dist: mutalyzer_hgvs_parser
Requires-Dist: pydantic
Requires-Dist: pydantic_settings
Requires-Dist: openai
Requires-Dist: opencv-python-headless
Requires-Dist: backoff
Requires-Dist: jmespath
Requires-Dist: azure-search-documents
Requires-Dist: semantic_kernel
Requires-Dist: importlib.resources
Dynamic: license-file
